data_transformations_project/__init__.py
data_transformations_project/test.py
data_transformations_project/transformations.py
data_transformations_project-0.1.1.dist-info/METADATA
data_transformations_project-0.1.1.dist-info/WHEEL
data_transformations_project-0.1.1.dist-info/RECORD
